{
  "annotations": {
    "list": [
      {
        "builtIn": 1,
        "datasource": {
          "type": "grafana",
          "uid": "-- Grafana --"
        },
        "enable": true,
        "hide": true,
        "iconColor": "rgba(0, 211, 255, 1)",
        "name": "Annotations & Alerts",
        "type": "dashboard"
      }
    ]
  },
  "editable": true,
  "fiscalYearStartMonth": 0,
  "graphTooltip": 0,
  "id": 1,
  "links": [],
  "panels": [
    {
      "datasource": {
        "type": "prometheus",
        "uid": "ff1q8t9nswsg0a"
      },
      "fieldConfig": {
        "defaults": {
          "color": {
            "mode": "thresholds"
          },
          "mappings": [],
          "thresholds": {
            "mode": "absolute",
            "steps": [
              {
                "color": "green",
                "value": 0
              },
              {
                "color": "red",
                "value": 80
              }
            ]
          }
        },
        "overrides": []
      },
      "gridPos": {
        "h": 8,
        "w": 12,
        "x": 0,
        "y": 0
      },
      "id": 2,
      "options": {
        "SVGBaseFix": true,
        "add100Percentage": true,
        "calcsMutation": "standard",
        "centerAlignContent": true,
        "codeData": "{\n  \"text\": \"Random text\"\n}",
        "css": ".painel-h1 {\n  color: gray;\n}",
        "dynamicData": false,
        "dynamicFieldDisplayValues": false,
        "dynamicHtmlGraphics": false,
        "dynamicProps": false,
        "html": "<div class=\"painel-h1\">\n  <h1>Monitoramento teste</h1>\n</div>",
        "onInit": "// Sets the text from customProperties\nconst htmlgraphicsText = htmlNode.getElementById('htmlgraphics-text');\n\nif (htmlgraphicsText) {\n  htmlgraphicsText.textContent = customProperties.text;\n\n  // Change the text color based on the theme\n  if (theme.isDark) {\n    htmlgraphicsText.style.color = 'green';\n  } else {\n    htmlgraphicsText.style.color = 'red';\n  }\n}\n",
        "onInitOnResize": false,
        "onRender": "// Sets the value from the first series on every refresh\nconst htmlgraphicsValue = htmlNode.getElementById('htmlgraphics-value');\n\nif (htmlgraphicsValue) {\n  const valueField = data.series[0]?.fields[1];\n  if (valueField) {\n    const length = valueField.values.length;\n    htmlgraphicsValue.textContent = valueField.values.get(length - 1);\n  } else {\n    htmlgraphicsValue.textContent = \"No data\"\n  }\n}\n",
        "overflow": "visible",
        "panelupdateOnMount": true,
        "reduceOptions": {
          "calcs": [
            "lastNotNull",
            "last",
            "firstNotNull",
            "first",
            "min",
            "max",
            "mean",
            "sum",
            "count",
            "range",
            "delta",
            "step",
            "diff",
            "logmin",
            "allIsZero",
            "allIsNull",
            "diffperc"
          ]
        },
        "renderOnMount": true,
        "rootCSS": "@import url('https://fonts.googleapis.com/css2?family=Poppins:ital,wght@0,100;0,200;0,300;0,400;0,500;0,600;0,700;0,800;0,900;1,100;1,200;1,300;1,400;1,500;1,600;1,700;1,800;1,900&display=swap');\n\nhtml, body { \n  background-image: linear-gradient(130deg, rgb(12, 12, 90), rgb(63, 63, 160));\n  font-family: \"Poppins\", sans-serif;\n  font-weight: 400;\n  font-style: normal; \n}\n\n.css-j9llvy {\n  border: 2px solid white;\n  border-radius: 7px;\n}\n\n.css-ly2u39 {\n    --rdg-background-color: transparent !important;\n}\n\n.css-ly2u39 .rdg-cell {\n    /* background-color: transparent; */\n    border: 1px solid white;\n}\n\n.css-1bgjk0t, .css-qn8k9s, .css-7g0550, .css-1lj8xfd-input-input {\n    background: transparent;\n}",
        "useGrafanaScrollbar": true
      },
      "pluginVersion": "2.2.1",
      "targets": [
        {
          "refId": "A"
        }
      ],
      "title": "",
      "transparent": true,
      "type": "gapit-htmlgraphics-panel"
    },
    {
      "datasource": {
        "type": "prometheus",
        "uid": "ff1q8t9nswsg0a"
      },
      "fieldConfig": {
        "defaults": {
          "color": {
            "mode": "thresholds"
          },
          "custom": {
            "align": "auto",
            "cellOptions": {
              "type": "auto"
            },
            "filterable": false,
            "footer": {
              "reducers": []
            },
            "inspect": false,
            "wrapHeaderText": false,
            "wrapText": false
          },
          "mappings": [],
          "thresholds": {
            "mode": "absolute",
            "steps": [
              {
                "color": "green",
                "value": 0
              }
            ]
          }
        },
        "overrides": []
      },
      "gridPos": {
        "h": 8,
        "w": 12,
        "x": 0,
        "y": 8
      },
      "id": 1,
      "options": {
        "cellHeight": "sm",
        "showHeader": true
      },
      "pluginVersion": "12.2.1",
      "targets": [
        {
          "datasource": {
            "type": "prometheus",
            "uid": "ff1q8t9nswsg0a"
          },
          "editorMode": "code",
          "expr": "usuarios_info * on(id) group_left(pais, plano) (usuarios_atividade or on() vector(0))",
          "legendFormat": "__auto",
          "range": true,
          "refId": "A"
        }
      ],
      "title": "New panel",
      "transparent": true,
      "type": "table"
    },
    {
      "datasource": {
        "type": "prometheus",
        "uid": "ff1q8t9nswsg0a"
      },
      "fieldConfig": {
        "defaults": {
          "color": {
            "mode": "thresholds"
          },
          "mappings": [],
          "thresholds": {
            "mode": "absolute",
            "steps": [
              {
                "color": "text",
                "value": 0
              }
            ]
          }
        },
        "overrides": []
      },
      "gridPos": {
        "h": 8,
        "w": 12,
        "x": 0,
        "y": 16
      },
      "id": 3,
      "options": {
        "colorMode": "value",
        "graphMode": "area",
        "justifyMode": "auto",
        "orientation": "auto",
        "percentChangeColorMode": "standard",
        "reduceOptions": {
          "calcs": [
            "lastNotNull"
          ],
          "fields": "",
          "values": false
        },
        "showPercentChange": false,
        "textMode": "auto",
        "wideLayout": true
      },
      "pluginVersion": "12.2.1",
      "targets": [
        {
          "datasource": {
            "type": "prometheus",
            "uid": "ff1q8t9nswsg0a"
          },
          "editorMode": "code",
          "expr": "usuarios_info * on(id) group_left(pais, plano) (usuarios_atividade or on() vector(0))",
          "legendFormat": "__auto",
          "range": true,
          "refId": "A"
        }
      ],
      "title": "New panel",
      "transformations": [
        {
          "id": "reduce",
          "options": {
            "reducers": [
              "sum"
            ]
          }
        }
      ],
      "transparent": true,
      "type": "stat"
    }
  ],
  "preload": false,
  "refresh": "10s",
  "schemaVersion": 42,
  "tags": [],
  "templating": {
    "list": []
  },
  "time": {
    "from": "now-6h",
    "to": "now"
  },
  "timepicker": {},
  "timezone": "browser",
  "title": "Testes Prometheus",
  "uid": "adfd675",
  "version": 12
}